[
  "Seleccionar Temporada",
  [],
  "Temporada 1",
  [
    {
      "cap": 1,
      "link": "https://watchsb.com/e/i5z26x5rvyio"
    },
    {
      "cap": 2,
      "link": "https://watchsb.com/e/m84tktxdy8dz"
    },
    {
      "cap": 3,
      "link": "https://watchsb.com/e/b9cr4dskf3sz"
    },
    {
      "cap": 4,
      "link": "https://watchsb.com/e/gcqs60sems06"
    },
    {
      "cap": 5,
      "link": "https://watchsb.com/e/svpj3rxtqvq2"
    },
    {
      "cap": 6,
      "link": "https://watchsb.com/e/lkpftrwmmivz"
    },
    {
      "cap": 7,
      "link": "https://watchsb.com/e/ik13vghalelp"
    },
    {
      "cap": 8,
      "link": "https://watchsb.com/e/r27rxowny1yv"
    },
    {
      "cap": 9,
      "link": "https://watchsb.com/e/iubq54ubk2y5"
    },
    {
      "cap": 10,
      "link": "https://watchsb.com/e/wem3obm2mzs0"
    },
    {
      "cap": 11,
      "link": "https://watchsb.com/e/rda9a7i2xhrn"
    },
    {
      "cap": 12,
      "link": "https://watchsb.com/e/3efwmktx4zgz"
    }
  ]
]
